pynbsim/__init__.py
pynbsim/_state.py
pynbsim/format.py
pynbsim/index.html
pynbsim/ji.py
pynbsim/progress.py
pynbsim/simulation.py
pynb_sim-0.2.3.dist-info/LICENSE
pynb_sim-0.2.3.dist-info/METADATA
pynb_sim-0.2.3.dist-info/WHEEL
pynb_sim-0.2.3.dist-info/top_level.txt
pynb_sim-0.2.3.dist-info/RECORD
