Metadata-Version: 2.1
Name: pynb-sim
Version: 0.2.3
Summary: Widgets & tools for large scale simulations inside of Python jupyter notebooks
Home-page: https://github.com/Helveg/pynb-sim
Author: Robin De Schepper
Author-email: robingilbert.deschepper@unipv.it
License: GPLv3
Platform: UNKNOWN
Classifier: Programming Language :: Python :: 3
Classifier: Operating System :: OS Independent
Requires-Dist: ipython
Provides-Extra: dev
Requires-Dist: sphinx ; extra == 'dev'
Requires-Dist: sphinx-rtd-theme ; extra == 'dev'
